periscope
