Metadata-Version: 1.0
Name: periscope-django
Version: 0.11
Summary: Periscope is an analysis tool for production SQL databases. This module provides the API for Periscope to communicate with your Django app.
Home-page: UNKNOWN
Author: Harry Glaser, Tom O'Neill
Author-email: harry.glaser@gmail.com, tom.oneill@live.com
License: UNKNOWN
Platform: UNKNOWN
